wandelscript/__init__.py
wandelscript/__main__.py
wandelscript/antlrvisitor.py
wandelscript/builtins.ws
wandelscript/cli.py
wandelscript/datatypes.py
wandelscript/examples.py
wandelscript/exception.py
wandelscript/ffi.py
wandelscript/frames.py
wandelscript/metamodel.py
wandelscript/migration.py
wandelscript/models.py
wandelscript/motions.py
wandelscript/operators.py
wandelscript/runner.py
wandelscript/runtime.py
wandelscript/simulation.py
wandelscript/version.py
wandelscript/builtins/__init__.py
wandelscript/builtins/array.py
wandelscript/builtins/assoc.py
wandelscript/builtins/controller.py
wandelscript/builtins/fetch.py
wandelscript/builtins/fs.py
wandelscript/builtins/math.py
wandelscript/builtins/pose.py
wandelscript/builtins/string.py
wandelscript/builtins/wait.py
wandelscript/examples/and_or.json
wandelscript/examples/and_or.ws
wandelscript/examples/array.config
wandelscript/examples/array.json
wandelscript/examples/array.ws
wandelscript/examples/assignment.json
wandelscript/examples/assignment.ws
wandelscript/examples/async_write.json
wandelscript/examples/async_write.ws
wandelscript/examples/blending.json
wandelscript/examples/blending.ws
wandelscript/examples/bool_negation.json
wandelscript/examples/bool_negation.ws
wandelscript/examples/builtins.json
wandelscript/examples/builtins.ws
wandelscript/examples/comments.json
wandelscript/examples/comments.ws
wandelscript/examples/context.json
wandelscript/examples/context.ws
wandelscript/examples/controller.cell.json
wandelscript/examples/controller.json
wandelscript/examples/controller.ws
wandelscript/examples/coordinate_systems.json
wandelscript/examples/coordinate_systems.ws
wandelscript/examples/default.cell.json
wandelscript/examples/default.json
wandelscript/examples/default.ws
wandelscript/examples/edge_pattern.json
wandelscript/examples/edge_pattern.ws
wandelscript/examples/edge_pattern_line.json
wandelscript/examples/edge_pattern_line.ws
wandelscript/examples/edge_pattern_manhattan.json
wandelscript-0.9.0.dist-info/METADATA
wandelscript-0.9.0.dist-info/WHEEL
wandelscript-0.9.0.dist-info/entry_points.txt
wandelscript-0.9.0.dist-info/licenses/LICENSE
wandelscript-0.9.0.dist-info/RECORD
