Metadata-Version: 2.4
Name: wandelscript
Version: 0.9.0
Summary: Wandelscript definition, parser, type checker & runtime
Author: Daniel Vorberg
Author-email: Christoph Biering <christoph.biering@wandelbots.com>, Dirk Sonnemann <dirk.sonnemann@wandelbots.com>, Andreas Langenhagen <andreas.langenhagen@wandelbots.com>, Mahsum Demir <mahsum.demir@wandelbots.com>
License-File: LICENSE
Requires-Python: ~=3.10
Requires-Dist: aiostream<0.7,>=0.6.1
Requires-Dist: antlr4-python3-runtime==4.13.1
Requires-Dist: anyio<5,>=4
Requires-Dist: exceptiongroup<2,>=1.2.2
Requires-Dist: geometricalgebra<0.2,>=0.1.3
Requires-Dist: numpy<3,>=2.2.1
Requires-Dist: pydantic<3,>=2.10.3
Requires-Dist: python-dotenv<2,>=1.0.1
Requires-Dist: typer[all]<0.16,>=0.12
Requires-Dist: wandelbots-nova>=1.11.0
